[
  {
    "id": "story_005",
    "categoryId": "home_relationships",
    "category": "家庭・人間関係",
    "title": "サンプル：[[先輩|せんぱい]]からの[[誘|さそ]]いを[[断|ことわ]]れず[[困|こま]]っている",
    "body": "（この[[記事|きじ]]はサンプルです。[[投稿|とうこう]]する[[際|さい]]の[[参考|さんこう]]にしてください）\n\n[[部活動|ぶかつどう]]の[[先輩|せんぱい]]から、[[休|やす]]みの[[日|ひ]]に[[遊|あそ]]びのために[[呼|よ]]び[[出|だ]]されることがよくあります。\n[[朝|あさ]]から[[夕方|ゆうがた]]まで[[連|つ]]れ[[回|まわ]]されたり、[[急|きゅう]]に[[予定|よてい]]を[[決|き]]められたりするため、[[負担|ふたん]]に[[感|かん]]じています。\n\n[[出|で]]かけるたびに[[交通費|こうつうひ]]や[[食事代|しょくじだい]]などがかかります。\n[[自由|じゆう]]に[[使|つか]]えるおこづかいは[[少|すく]]ないので、[[何度|なんど]]も[[付|つ]]き[[合|あ]]っていると、お[[金|かね]]が[[足|た]]りなくなることもあります。\n\n[[部活動|ぶかつどう]]で[[毎日|まいにち]]のように[[顔|かお]]を[[合|あ]]わせる[[先輩|せんぱい]]なので、[[断|ことわ]]ったら[[関係|かんけい]]が[[悪|わる]]くなったり、[[部活動|ぶかつどう]]で[[気|き]]まずくなったりするのではないかと[[思|おも]]い、なかなか[[断|ことわ]]れません。\n\n[[先輩|せんぱい]]は[[気軽|きがる]]に[[誘|さそ]]っているだけかもしれませんが、[[断|ことわ]]れないまま[[毎回|まいかい]][[付|つ]]き[[合|あ]]うことがつらくなってきました。\nどのように[[伝|つた]]えれば、[[相手|あいて]]を[[怒|おこ]]らせずに[[断|ことわ]]れるのか[[悩|なや]]んでいます。",
    "publishedAt": "2026-07-13",
    "updatedAt": "2026-07-13"
  }
]
